digital_logic/div3_old.v
module div_3(
    input           clk_in,
    input           rst_n,
    output          clk_out
);

    reg [1:0] r_cnt;

    // 1. 计数器逻辑 (保持你原来的写法)
    always @(posedge clk_in or negedge rst_n) begin
        if(!rst_n)
            r_cnt <= 2'd0;
        else 
            r_cnt <= (r_cnt == 2'd2) ? 2'd0 : r_cnt + 1;
    end

    reg clk_p;
    reg clk_n;

    // 2. 上升沿产生脉冲 clk_p
    // 当计数为 2 时拉高，其余时间拉低 (高电平占 1/3)
    always @(posedge clk_in or negedge rst_n) begin
        if(!rst_n)
            clk_p <= 1'b0;
        else if (r_cnt == 2'd2) 
            clk_p <= 1'b1;
        else 
            clk_p <= 1'b0;
    end

    // 3. 下降沿产生脉冲 clk_n
    // 同样在计数为 2 时拉高 (注意：r_cnt 是在上升沿变的，所以在下降沿采样的 r_cnt 值还是 2)
    always @(negedge clk_in or negedge rst_n) begin
        if(!rst_n)
            clk_n <= 1'b0;
        else if (r_cnt == 2'd2) 
            clk_n <= 1'b1;
        else 
            clk_n <= 1'b0;
    end

    // 4. 组合输出
    // 错开半个周期的两个脉冲相“或”，得到 1.5 个周期的高电平
    assign clk_out = clk_p | clk_n;

endmodule

// generate testbench for module div_3

digital_logic/div_3/tb_div3_old.v
`timescale 1ns/1ps

module tb_div3;

    reg clk_in;
    reg rst_n;
    wire clk_out;

    // Instantiate DUT
    div_3 uut (
        .clk_in(clk_in),
        .rst_n(rst_n),
        .clk_out(clk_out)
    );

    // Clock: 100 MHz -> period 10 ns
    initial clk_in = 1'b0;
    always #5 clk_in = ~clk_in;

    // Reset
    initial begin
        rst_n = 1'b0;
        #30; // hold reset for two clock cycles
        rst_n = 1'b1;
    end

    // Waveform dump (for Icarus/GTKWave)
    initial begin
        $dumpfile("div3_tb.vcd");
        $dumpvars(0, tb_div3);
    end

    // Simple period measurement on clk_out
    time last_time;
    time period;

    initial begin
        last_time = 0;
        #2000; // run long enough to observe several periods
        $display("Simulation finished.");
        $finish;
    end

    always @(posedge clk_out) begin
        if (last_time != 0) begin
            period = $time - last_time;
            $display("@%0t ns: clk_out posedge, period = %0t ns", $time, period);
            // crude check: expected ~30 ns for 100 MHz input divided by 3
            if (period < 28 || period > 32) begin
                $display("WARNING: measured period %0t ns outside expected ~30 ns", period);
            end
        end
        last_time = $time;
    end

    // Optional textual monitor
    initial begin
        $display("Starting div_3 testbench");
        $display("Time\tclk_in\tclk_out");
        forever begin
            @(posedge clk_in);
            $display("%0t\t%b\t%b", $time, clk_in, clk_out);
        end
    end

endmodule

digital_logic/div_3/div3_tb.vcd
$date
	Tue Dec 09 16:40:05 2025
$end
$version
	ModelSim Version 2020.4
$end
$timescale
	1ps
$end

$scope module tb_div3 $end
$var reg 1 ! clk_in $end
$var reg 1 " rst_n $end
$var wire 1 # clk_out $end
$var time 64 $ last_time $end
$var time 64 % period $end

$scope module uut $end
$var wire 1 & clk_in $end
$var wire 1 ' rst_n $end
$var wire 1 # clk_out $end
$var reg 2 ( r_cnt [1:0] $end
$var reg 1 ) clk_p $end
$var reg 1 * clk_n $end
$upscope $end
$upscope $end
$enddefinitions $end
#0
$dumpvars
0!
0"
b0 (
0)
0*
b0 $
bx %
0#
0'
0&
$end
#5000
1!
1&
#10000
0!
0&
#15000
1!
1&
#20000
0!
0&
#25000
1!
1&
#30000
1"
0!
1'
0&
#35000
1!
1&
b1 (
#40000
0!
0&
#45000
1!
1&
b10 (
#50000
0!
0&
1*
1#
b110010 $
#55000
1!
1&
b0 (
1)
#60000
0!
0&
0*
#65000
1!
1&
b1 (
0)
0#
#70000
0!
0&
#75000
1!
1&
b10 (
#80000
0!
0&
1*
1#
b11110 %
b1010000 $
#85000
1!
1&
b0 (
1)
#90000
0!
0&
0*
#95000
1!
1&
b1 (
0)
0#
#100000
0!
0&
#105000
1!
1&
b10 (
#110000
0!
0&
1*
1#
b1101110 $
#115000
1!
1&
b0 (
1)
#120000
0!
0&
0*
#125000
1!
1&
b1 (
0)
0#
#130000
0!
0&
#135000
1!
1&
b10 (
#140000
0!
0&
1*
1#
b10001100 $
#145000
1!
1&
b0 (
1)
#150000
0!
0&
0*
#155000
1!
1&
b1 (
0)
0#
#160000
0!
0&
#165000
1!
1&
b10 (
#170000
0!
0&
1*
1#
b10101010 $
#175000
1!
1&
b0 (
1)
#180000
0!
0&
0*
#185000
1!
1&
b1 (
0)
0#
#190000
0!
0&
#195000
1!
1&
b10 (
#200000
0!
0&
1*
1#
b11001000 $
#205000
1!
1&
b0 (
1)
#210000
0!
0&
0*
#215000
1!
1&
b1 (
0)
0#
#220000
0!
0&
#225000
1!
1&
b10 (
#230000
0!
0&
1*
1#
b11100110 $
#235000
1!
1&
b0 (
1)
#240000
0!
0&
0*
#245000
1!
1&
b1 (
0)
0#
#250000
0!
0&
#255000
1!
1&
b10 (
#260000
0!
0&
1*
1#
b100000100 $
#265000
1!
1&
b0 (
1)
#270000
0!
0&
0*
#275000
1!
1&
b1 (
0)
0#
#280000
0!
0&
#285000
1!
1&
b10 (
#290000
0!
0&
1*
1#
b100100010 $
#295000
1!
1&
b0 (
1)
#300000
0!
0&
0*
#305000
1!
1&
b1 (
0)
0#
#310000
0!
0&
#315000
1!
1&
b10 (
#320000
0!
0&
1*
1#
b101000000 $
#325000
1!
1&
b0 (
1)
#330000
0!
0&
0*
#335000
1!
1&
b1 (
0)
0#
#340000
0!
0&
#345000
1!
1&
b10 (
#350000
0!
0&
1*
1#
b101011110 $
#355000
1!
1&
b0 (
1)
#360000
0!
0&
0*
#365000
1!
1&
b1 (
0)
0#
#370000
0!
0&
#375000
1!
1&
b10 (
#380000
0!
0&
1*
1#
b101111100 $
#385000
1!
1&
b0 (
1)
#390000
0!
0&
0*
#395000
1!
1&
b1 (
0)
0#
#400000
0!
0&
#405000
1!
1&
b10 (
#410000
0!
0&
1*
1#
b110011010 $
#415000
1!
1&
b0 (
1)
#420000
0!
0&
0*
#425000
1!
1&
b1 (
0)
0#
#430000
0!
0&
#435000
1!
1&
b10 (
#440000
0!
0&
1*
1#
b110111000 $
#445000
1!
1&
b0 (
1)
#450000
0!
0&
0*
#455000
1!
1&
b1 (
0)
0#
#460000
0!
0&
#465000
1!
1&
b10 (
#470000
0!
0&
1*
1#
b111010110 $
#475000
1!
1&
b0 (
1)
#480000
0!
0&
0*
#485000
1!
1&
b1 (
0)
0#
#490000
0!
0&
#495000
1!
1&
b10 (
#500000
0!
0&
1*
1#
b111110100 $
#505000
1!
1&
b0 (
1)
#510000
0!
0&
0*
#515000
1!
1&
b1 (
0)
0#
#520000
0!
0&
#525000
1!
1&
b10 (
#530000
0!
0&
1*
1#
b1000010010 $
#535000
1!
1&
b0 (
1)
#540000
0!
0&
0*
#545000
1!
1&
b1 (
0)
0#
#550000
0!
0&
#555000
1!
1&
b10 (
#560000
0!
0&
1*
1#
b1000110000 $
#565000
1!
1&
b0 (
1)
#570000
0!
0&
0*
#575000
1!
1&
b1 (
0)
0#
#580000
0!
0&
#585000
1!
1&
b10 (
#590000
0!
0&
1*
1#
b1001001110 $
#595000
1!
1&
b0 (
1)
#600000
0!
0&
0*
#605000
1!
1&
b1 (
0)
0#
#610000
0!
0&
#615000
1!
1&
b10 (
#620000
0!
0&
1*
1#
b1001101100 $
#625000
1!
1&
b0 (
1)
#630000
0!
0&
0*
#635000
1!
1&
b1 (
0)
0#
#640000
0!
0&
#645000
1!
1&
b10 (
#650000
0!
0&
1*
1#
b1010001010 $
#655000
1!
1&
b0 (
1)
#660000
0!
0&
0*
#665000
1!
1&
b1 (
0)
0#
#670000
0!
0&
#675000
1!
1&
b10 (
#680000
0!
0&
1*
1#
b1010101000 $
#685000
1!
1&
b0 (
1)
#690000
0!
0&
0*
#695000
1!
1&
b1 (
0)
0#
#700000
0!
0&
#705000
1!
1&
b10 (
#710000
0!
0&
1*
1#
b1011000110 $
#715000
1!
1&
b0 (
1)
#720000
0!
0&
0*
#725000
1!
1&
b1 (
0)
0#
#730000
0!
0&
#735000
1!
1&
b10 (
#740000
0!
0&
1*
1#
b1011100100 $
#745000
1!
1&
b0 (
1)
#750000
0!
0&
0*
#755000
1!
1&
b1 (
0)
0#
#760000
0!
0&
#765000
1!
1&
b10 (
#770000
0!
0&
1*
1#
b1100000010 $
#775000
1!
1&
b0 (
1)
#780000
0!
0&
0*
#785000
1!
1&
b1 (
0)
0#
#790000
0!
0&
#795000
1!
1&
b10 (
#800000
0!
0&
1*
1#
b1100100000 $
#805000
1!
1&
b0 (
1)
#810000
0!
0&
0*
#815000
1!
1&
b1 (
0)
0#
#820000
0!
0&
#825000
1!
1&
b10 (
#830000
0!
0&
1*
1#
b1100111110 $
#835000
1!
1&
b0 (
1)
#840000
0!
0&
0*
#845000
1!
1&
b1 (
0)
0#
#850000
0!
0&
#855000
1!
1&
b10 (
#860000
0!
0&
1*
1#
b1101011100 $
#865000
1!
1&
b0 (
1)
#870000
0!
0&
0*
#875000
1!
1&
b1 (
0)
0#
#880000
0!
0&
#885000
1!
1&
b10 (
#890000
0!
0&
1*
1#
b1101111010 $
#895000
1!
1&
b0 (
1)
#900000
0!
0&
0*
#905000
1!
1&
b1 (
0)
0#
#910000
0!
0&
#915000
1!
1&
b10 (
#920000
0!
0&
1*
1#
b1110011000 $
#925000
1!
1&
b0 (
1)
#930000
0!
0&
0*
#935000
1!
1&
b1 (
0)
0#
#940000
0!
0&
#945000
1!
1&
b10 (
#950000
0!
0&
1*
1#
b1110110110 $
#955000
1!
1&
b0 (
1)
#960000
0!
0&
0*
#965000
1!
1&
b1 (
0)
0#
#970000
0!
0&
#975000
1!
1&
b10 (
#980000
0!
0&
1*
1#
b1111010100 $
#985000
1!
1&
b0 (
1)
#990000
0!
0&
0*
#995000
1!
1&
b1 (
0)
0#
#1000000
0!
0&
#1005000
1!
1&
b10 (
#1010000
0!
0&
1*
1#
b1111110010 $
#1015000
1!
1&
b0 (
1)
#1020000
0!
0&
0*
#1025000
1!
1&
b1 (
0)
0#
#1030000
0!
0&
#1035000
1!
1&
b10 (
#1040000
0!
0&
1*
1#
b10000010000 $
#1045000
1!
1&
b0 (
1)
#1050000
0!
0&
0*
#1055000
1!
1&
b1 (
0)
0#
#1060000
0!
0&
#1065000
1!
1&
b10 (
#1070000
0!
0&
1*
1#
b10000101110 $
#1075000
1!
1&
b0 (
1)
#1080000
0!
0&
0*
#1085000
1!
1&
b1 (
0)
0#
#1090000
0!
0&
#1095000
1!
1&
b10 (
#1100000
0!
0&
1*
1#
b10001001100 $
#1105000
1!
1&
b0 (
1)
#1110000
0!
0&
0*
#1115000
1!
1&
b1 (
0)
0#
#1120000
0!
0&
#1125000
1!
1&
b10 (
#1130000
0!
0&
1*
1#
b10001101010 $
#1135000
1!
1&
b0 (
1)
#1140000
0!
0&
0*
#1145000
1!
1&
b1 (
0)
0#
#1150000
0!
0&
#1155000
1!
1&
b10 (
#1160000
0!
0&
1*
1#
b10010001000 $
#1165000
1!
1&
b0 (
1)
#1170000
0!
0&
0*
#1175000
1!
1&
b1 (
0)
0#
#1180000
0!
0&
#1185000
1!
1&
b10 (
#1190000
0!
0&
1*
1#
b10010100110 $
#1195000
1!
1&
b0 (
1)
#1200000
0!
0&
0*
#1205000
1!
1&
b1 (
0)
0#
#1210000
0!
0&
#1215000
1!
1&
b10 (
#1220000
0!
0&
1*
1#
b10011000100 $
#1225000
1!
1&
b0 (
1)
#1230000
0!
0&
0*
#1235000
1!
1&
b1 (
0)
0#
#1240000
0!
0&
#1245000
1!
1&
b10 (
#1250000
0!
0&
1*
1#
b10011100010 $
#1255000
1!
1&
b0 (
1)
#1260000
0!
0&
0*
#1265000
1!
1&
b1 (
0)
0#
#1270000
0!
0&
#1275000
1!
1&
b10 (
#1280000
0!
0&
1*
1#
b10100000000 $
#1285000
1!
1&
b0 (
1)
#1290000
0!
0&
0*
#1295000
1!
1&
b1 (
0)
0#
#1300000
0!
0&
#1305000
1!
1&
b10 (
#1310000
0!
0&
1*
1#
b10100011110 $
#1315000
1!
1&
b0 (
1)
#1320000
0!
0&
0*
#1325000
1!
1&
b1 (
0)
0#
#1330000
0!
0&
#1335000
1!
1&
b10 (
#1340000
0!
0&
1*
1#
b10100111100 $
#1345000
1!
1&
b0 (
1)
#1350000
0!
0&
0*
#1355000
1!
1&
b1 (
0)
0#
#1360000
0!
0&
#1365000
1!
1&
b10 (
#1370000
0!
0&
1*
1#
b10101011010 $
#1375000
1!
1&
b0 (
1)
#1380000
0!
0&
0*
#1385000
1!
1&
b1 (
0)
0#
#1390000
0!
0&
#1395000
1!
1&
b10 (
#1400000
0!
0&
1*
1#
b10101111000 $
#1405000
1!
1&
b0 (
1)
#1410000
0!
0&
0*
#1415000
1!
1&
b1 (
0)
0#
#1420000
0!
0&
#1425000
1!
1&
b10 (
#1430000
0!
0&
1*
1#
b10110010110 $
#1435000
1!
1&
b0 (
1)
#1440000
0!
0&
0*
#1445000
1!
1&
b1 (
0)
0#
#1450000
0!
0&
#1455000
1!
1&
b10 (
#1460000
0!
0&
1*
1#
b10110110100 $
#1465000
1!
1&
b0 (
1)
#1470000
0!
0&
0*
#1475000
1!
1&
b1 (
0)
0#
#1480000
0!
0&
#1485000
1!
1&
b10 (
#1490000
0!
0&
1*
1#
b10111010010 $
#1495000
1!
1&
b0 (
1)
#1500000
0!
0&
0*
#1505000
1!
1&
b1 (
0)
0#
#1510000
0!
0&
#1515000
1!
1&
b10 (
#1520000
0!
0&
1*
1#
b10111110000 $
#1525000
1!
1&
b0 (
1)
#1530000
0!
0&
0*
#1535000
1!
1&
b1 (
0)
0#
#1540000
0!
0&
#1545000
1!
1&
b10 (
#1550000
0!
0&
1*
1#
b11000001110 $
#1555000
1!
1&
b0 (
1)
#1560000
0!
0&
0*
#1565000
1!
1&
b1 (
0)
0#
#1570000
0!
0&
#1575000
1!
1&
b10 (
#1580000
0!
0&
1*
1#
b11000101100 $
#1585000
1!
1&
b0 (
1)
#1590000
0!
0&
0*
#1595000
1!
1&
b1 (
0)
0#
#1600000
0!
0&
#1605000
1!
1&
b10 (
#1610000
0!
0&
1*
1#
b11001001010 $
#1615000
1!
1&
b0 (
1)
#1620000
0!
0&
0*
#1625000
1!
1&
b1 (
0)
0#
#1630000
0!
0&
#1635000
1!
1&
b10 (
#1640000
0!
0&
1*
1#
b11001101000 $
#1645000
1!
1&
b0 (
1)
#1650000
0!
0&
0*
#1655000
1!
1&
b1 (
0)
0#
#1660000
0!
0&
#1665000
1!
1&
b10 (
#1670000
0!
0&
1*
1#
b11010000110 $
#1675000
1!
1&
b0 (
1)
#1680000
0!
0&
0*
#1685000
1!
1&
b1 (
0)
0#
#1690000
0!
0&
#1695000
1!
1&
b10 (
#1700000
0!
0&
1*
1#
b11010100100 $
#1705000
1!
1&
b0 (
1)
#1710000
0!
0&
0*
#1715000
1!
1&
b1 (
0)
0#
#1720000
0!
0&
#1725000
1!
1&
b10 (
#1730000
0!
0&
1*
1#
b11011000010 $
#1735000
1!
1&
b0 (
1)
#1740000
0!
0&
0*
#1745000
1!
1&
b1 (
0)
0#
#1750000
0!
0&
#1755000
1!
1&
b10 (
#1760000
0!
0&
1*
1#
b11011100000 $
#1765000
1!
1&
b0 (
1)
#1770000
0!
0&
0*
#1775000
1!
1&
b1 (
0)
0#
#1780000
0!
0&
#1785000
1!
1&
b10 (
#1790000
0!
0&
1*
1#
b11011111110 $
#1795000
1!
1&
b0 (
1)
#1800000
0!
0&
0*
#1805000
1!
1&
b1 (
0)
0#
#1810000
0!
0&
#1815000
1!
1&
b10 (
#1820000
0!
0&
1*
1#
b11100011100 $
#1825000
1!
1&
b0 (
1)
#1830000
0!
0&
0*
#1835000
1!
1&
b1 (
0)
0#
#1840000
0!
0&
#1845000
1!
1&
b10 (
#1850000
0!
0&
1*
1#
b11100111010 $
#1855000
1!
1&
b0 (
1)
#1860000
0!
0&
0*
#1865000
1!
1&
b1 (
0)
0#
#1870000
0!
0&
#1875000
1!
1&
b10 (
#1880000
0!
0&
1*
1#
b11101011000 $
#1885000
1!
1&
b0 (
1)
#1890000
0!
0&
0*
#1895000
1!
1&
b1 (
0)
0#
#1900000
0!
0&
#1905000
1!
1&
b10 (
#1910000
0!
0&
1*
1#
b11101110110 $
#1915000
1!
1&
b0 (
1)
#1920000
0!
0&
0*
#1925000
1!
1&
b1 (
0)
0#
#1930000
0!
0&
#1935000
1!
1&
b10 (
#1940000
0!
0&
1*
1#
b11110010100 $
#1945000
1!
1&
b0 (
1)
#1950000
0!
0&
0*
#1955000
1!
1&
b1 (
0)
0#
#1960000
0!
0&
#1965000
1!
1&
b10 (
#1970000
0!
0&
1*
1#
b11110110010 $
#1975000
1!
1&
b0 (
1)
#1980000
0!
0&
0*
#1985000
1!
1&
b1 (
0)
0#
#1990000
0!
0&
#1995000
1!
1&
b10 (
